gpt_optimizer/__init__.py
gpt_optimizer-0.0.1.dist-info/METADATA
gpt_optimizer-0.0.1.dist-info/WHEEL
gpt_optimizer-0.0.1.dist-info/top_level.txt
gpt_optimizer-0.0.1.dist-info/RECORD
