Metadata-Version: 2.1
Name: gpt-optimizer
Version: 0.0.1
Requires-Dist: openai
Requires-Dist: beautifulsoup4
Requires-Dist: requests
Requires-Dist: google-api-python-client
